LICENSE
MANIFEST.in
setup.py
gmapsmarkers/__init__.py
gmapsmarkers/conf.py
gmapsmarkers/fields.py
gmapsmarkers/widgets.py
gmapsmarkers/static/gmapsmarkers/css/gmaps.css
gmapsmarkers/static/gmapsmarkers/img/gmaps-icon.png
gmapsmarkers/static/gmapsmarkers/js/.gmap.js.un~
gmapsmarkers/static/gmapsmarkers/js/.gmaps.js.un~
gmapsmarkers/static/gmapsmarkers/js/.gmaps__init.js.un~
gmapsmarkers/static/gmapsmarkers/js/gmaps.js
gmapsmarkers/static/gmapsmarkers/js/gmaps__init.js
gmapsmarkers/static/gmapsmarkers/js/jquery-2.1.0.min.js
gmapsmarkers/static/gmapsmarkers/select2-3.4.8/.gitignore
gmapsmarkers/static/gmapsmarkers/select2-3.4.8/LICENSE
gmapsmarkers/static/gmapsmarkers/select2-3.4.8/README.md
gmapsmarkers/static/gmapsmarkers/select2-3.4.8/bower.json
gmapsmarkers/static/gmapsmarkers/select2-3.4.8/component.json
gmapsmarkers/static/gmapsmarkers/select2-3.4.8/composer.json
gmapsmarkers/static/gmapsmarkers/select2-3.4.8/package.json
gmapsmarkers/static/gmapsmarkers/select2-3.4.8/release.sh
gmapsmarkers/static/gmapsmarkers/select2-3.4.8/select2-bootstrap.css
gmapsmarkers/static/gmapsmarkers/select2-3.4.8/select2-spinner.gif
gmapsmarkers/static/gmapsmarkers/select2-3.4.8/select2.css
gmapsmarkers/static/gmapsmarkers/select2-3.4.8/select2.jquery.json
gmapsmarkers/static/gmapsmarkers/select2-3.4.8/select2.js
gmapsmarkers/static/gmapsmarkers/select2-3.4.8/select2.min.js
gmapsmarkers/static/gmapsmarkers/select2-3.4.8/select2.png
gmapsmarkers/static/gmapsmarkers/select2-3.4.8/select2_locale_ar.js
gmapsmarkers/static/gmapsmarkers/select2-3.4.8/select2_locale_bg.js
gmapsmarkers/static/gmapsmarkers/select2-3.4.8/select2_locale_ca.js
gmapsmarkers/static/gmapsmarkers/select2-3.4.8/select2_locale_cs.js
gmapsmarkers/static/gmapsmarkers/select2-3.4.8/select2_locale_da.js
gmapsmarkers/static/gmapsmarkers/select2-3.4.8/select2_locale_de.js
gmapsmarkers/static/gmapsmarkers/select2-3.4.8/select2_locale_el.js
gmapsmarkers/static/gmapsmarkers/select2-3.4.8/select2_locale_en.js.template
twentytab_gmapsmarkers.egg-info/PKG-INFO
twentytab_gmapsmarkers.egg-info/SOURCES.txt
twentytab_gmapsmarkers.egg-info/dependency_links.txt
twentytab_gmapsmarkers.egg-info/requires.txt
twentytab_gmapsmarkers.egg-info/top_level.txt