Metadata-Version: 1.0
Name: twentytab-gmapsmarkers
Version: 0.17
Summary: A django widget with Select2 integration that uses google geocode api to search places and create maps with markers
Home-page: https://github.com/20tab/twentytab-gmapsmarkers
Author: 20tab S.r.l.
Author-email: info@20tab.com
License: MIT License
Platform: UNKNOWN
